{"is_source_file": false, "format": "", "description": "", "external_files": [], "external_methods": [], "published": [], "classes": [], "methods": [], "calls": [], "search-terms": [], "state": 2, "file_id": 3, "knowledge_revision": 47, "git_revision": "a640a33bb77d63a087c08a8a8aacb437c9cfaaae", "hash": "291e6b6c7bf0f74d1dc17b90c3a2d721", "format-version": 4, "code-base-name": "blog_frontend", "filename": "blog_frontend/src/index.css", "revision_history": [{"47": "a640a33bb77d63a087c08a8a8aacb437c9cfaaae"}]}